enterprise_gateway/__init__.py
enterprise_gateway/__main__.py
enterprise_gateway/_version.py
enterprise_gateway/enterprisegatewayapp.py
enterprise_gateway/mixins.py
enterprise_gateway/base/__init__.py
enterprise_gateway/base/handlers.py
enterprise_gateway/client/__init__.py
enterprise_gateway/client/gateway_client.py
enterprise_gateway/itests/__init__.py
enterprise_gateway/itests/test_authorization.py
enterprise_gateway/itests/test_base.py
enterprise_gateway/itests/test_python_kernel.py
enterprise_gateway/itests/test_r_kernel.py
enterprise_gateway/itests/test_scala_kernel.py
enterprise_gateway/itests/kernels/authorization_test/kernel.json
enterprise_gateway/services/__init__.py
enterprise_gateway/services/api/__init__.py
enterprise_gateway/services/api/handlers.py
enterprise_gateway/services/api/swagger.json
enterprise_gateway/services/api/swagger.yaml
enterprise_gateway/services/kernels/__init__.py
enterprise_gateway/services/kernels/handlers.py
enterprise_gateway/services/kernels/remotemanager.py
enterprise_gateway/services/kernelspecs/__init__.py
enterprise_gateway/services/kernelspecs/handlers.py
enterprise_gateway/services/kernelspecs/kernelspec_cache.py
enterprise_gateway/services/processproxies/__init__.py
enterprise_gateway/services/processproxies/conductor.py
enterprise_gateway/services/processproxies/container.py
enterprise_gateway/services/processproxies/crd.py
enterprise_gateway/services/processproxies/distributed.py
enterprise_gateway/services/processproxies/docker_swarm.py
enterprise_gateway/services/processproxies/k8s.py
enterprise_gateway/services/processproxies/processproxy.py
enterprise_gateway/services/processproxies/spark_operator.py
enterprise_gateway/services/processproxies/yarn.py
enterprise_gateway/services/sessions/__init__.py
enterprise_gateway/services/sessions/handlers.py
enterprise_gateway/services/sessions/kernelsessionmanager.py
enterprise_gateway/services/sessions/sessionmanager.py
enterprise_gateway/tests/__init__.py
jupyter_enterprise_gateway-3.2.3.dist-info/METADATA
jupyter_enterprise_gateway-3.2.3.dist-info/WHEEL
jupyter_enterprise_gateway-3.2.3.dist-info/entry_points.txt
jupyter_enterprise_gateway-3.2.3.dist-info/licenses/LICENSE.md
jupyter_enterprise_gateway-3.2.3.dist-info/RECORD
