Metadata-Version: 2.1
Name: jupyter_enterprise_gateway
Version: 3.2.3
Summary: A web server for spawning and communicating with remote Jupyter kernels
Project-URL: Homepage, http://github.com/jupyter/enterprise_gateway
Author-email: Jupyter Development Team <jupyter@googlegroups.com>
License: # Licensing terms
License-File: LICENSE.md
Keywords: Cloud,Interactive,Interpreter,Kernel,Web
Classifier: Intended Audience :: Developers
Classifier: Intended Audience :: Science/Research
Classifier: Intended Audience :: System Administrators
Classifier: License :: OSI Approved :: BSD License
Classifier: Programming Language :: Python
Classifier: Programming Language :: Python :: 3
Classifier: Programming Language :: Python :: 3 :: Only
Classifier: Programming Language :: Python :: 3.8
Classifier: Programming Language :: Python :: 3.9
Classifier: Programming Language :: Python :: 3.10
Classifier: Programming Language :: Python :: 3.11
Requires-Python: >=3.8
Requires-Dist: docker>=3.5.0
Requires-Dist: future
Requires-Dist: jinja2>=3.1
Requires-Dist: jupyter-client<7,>=6.1.12
Requires-Dist: jupyter-core>=4.7.0
Requires-Dist: jupyter-server<2.0,>=1.7
Requires-Dist: kubernetes>=18.20.0
Requires-Dist: paramiko>=2.11
Requires-Dist: pexpect>=4.8.0
Requires-Dist: pycryptodomex>=3.9.7
Requires-Dist: pyzmq<25.0,>=20.0
Requires-Dist: requests>=2.14.2
Requires-Dist: tornado>=6.1
Requires-Dist: traitlets>=5.3.0
Requires-Dist: watchdog>=2.1.3
Requires-Dist: yarn-api-client>=1.0
Provides-Extra: lint
Requires-Dist: black[jupyter]==24.2.0; extra == 'lint'
Requires-Dist: mdformat-gfm>=0.3.5; extra == 'lint'
Requires-Dist: mdformat>0.7; extra == 'lint'
Requires-Dist: ruff==0.2.2; extra == 'lint'
Provides-Extra: test
Requires-Dist: coverage; extra == 'test'
Requires-Dist: ipykernel; extra == 'test'
Requires-Dist: pre-commit; extra == 'test'
Requires-Dist: pytest; extra == 'test'
Requires-Dist: pytest-tornasync; extra == 'test'
Requires-Dist: websocket-client; extra == 'test'
